<annotation>
	<folder>Hammer - Listas para label</folder>
	<filename>Hammer (140).JPG</filename>
	<path>C:\Users\Usuario\Pictures\SharkID\Hammer - Listas para label-20210118T005033Z-001\Hammer - Listas para label\Hammer (140).JPG</path>
	<source>
		<database>Unknown</database>
	</source>
	<size>
		<width>696</width>
		<height>464</height>
		<depth>3</depth>
	</size>
	<segmented>0</segmented>
	<object>
		<name>Hammer</name>
		<pose>Unspecified</pose>
		<truncated>0</truncated>
		<difficult>0</difficult>
		<bndbox>
			<xmin>172</xmin>
			<ymin>276</ymin>
			<xmax>332</xmax>
			<ymax>398</ymax>
		</bndbox>
	</object>
</annotation>
