<annotation>
	<folder>Hammer - Listas para label</folder>
	<filename>Hammer (198).jpg</filename>
	<path>C:\Users\Usuario\Pictures\SharkID\Hammer - Listas para label-20210118T005033Z-001\Hammer - Listas para label\Hammer (198).jpg</path>
	<source>
		<database>Unknown</database>
	</source>
	<size>
		<width>724</width>
		<height>484</height>
		<depth>3</depth>
	</size>
	<segmented>0</segmented>
	<object>
		<name>Hammer</name>
		<pose>Unspecified</pose>
		<truncated>0</truncated>
		<difficult>0</difficult>
		<bndbox>
			<xmin>233</xmin>
			<ymin>194</ymin>
			<xmax>649</xmax>
			<ymax>382</ymax>
		</bndbox>
	</object>
	<object>
		<name>Hammer</name>
		<pose>Unspecified</pose>
		<truncated>0</truncated>
		<difficult>0</difficult>
		<bndbox>
			<xmin>358</xmin>
			<ymin>199</ymin>
			<xmax>566</xmax>
			<ymax>346</ymax>
		</bndbox>
	</object>
</annotation>
