<annotation>
	<folder>Mako Label</folder>
	<filename>Mako (229).JPG</filename>
	<path>C:\Users\Samuel\Desktop\Mako Label\Mako (229).JPG</path>
	<source>
		<database>Unknown</database>
	</source>
	<size>
		<width>696</width>
		<height>464</height>
		<depth>3</depth>
	</size>
	<segmented>0</segmented>
	<object>
		<name>Mako</name>
		<pose>Unspecified</pose>
		<truncated>0</truncated>
		<difficult>0</difficult>
		<bndbox>
			<xmin>379</xmin>
			<ymin>218</ymin>
			<xmax>638</xmax>
			<ymax>317</ymax>
		</bndbox>
	</object>
</annotation>
